ezinstall/__init__.py
ezinstall/__init__.pyc
ezinstall/ezinstall.py
ezinstall/ezinstall.pyc
ezinstall/zzz_ezinstall.py
ezinstall-0.0.2.dist-info/DESCRIPTION.rst
ezinstall-0.0.2.dist-info/METADATA
ezinstall-0.0.2.dist-info/RECORD
ezinstall-0.0.2.dist-info/WHEEL
ezinstall-0.0.2.dist-info/metadata.json
ezinstall-0.0.2.dist-info/top_level.txt
